gravtr-0.0.3.dist-info/DESCRIPTION.rst
gravtr-0.0.3.dist-info/metadata.json
gravtr-0.0.3.dist-info/top_level.txt
gravtr-0.0.3.dist-info/RECORD
gravtr-0.0.3.dist-info/METADATA
gravtr-0.0.3.dist-info/WHEEL
gravtr/__init__.py
